amodbus/__init__.py
amodbus/client/__init__.py
amodbus/client/base.py
amodbus/client/mixin.py
amodbus/client/serial.py
amodbus/client/tcp.py
amodbus/client/tls.py
amodbus/client/udp.py
amodbus/constants.py
amodbus/datastore/__init__.py
amodbus/datastore/context.py
amodbus/datastore/remote.py
amodbus/datastore/simulator.py
amodbus/datastore/store.py
amodbus/device.py
amodbus/events.py
amodbus/exceptions.py
amodbus/framer/__init__.py
amodbus/framer/ascii.py
amodbus/framer/base.py
amodbus/framer/rtu.py
amodbus/framer/socket.py
amodbus/framer/tls.py
amodbus/logging.py
amodbus/payload.py
amodbus/pdu/__init__.py
amodbus/pdu/bit_message.py
amodbus/pdu/decoders.py
amodbus/pdu/diag_message.py
amodbus/pdu/file_message.py
amodbus/pdu/mei_message.py
amodbus/pdu/other_message.py
amodbus/pdu/pdu.py
amodbus/pdu/register_message.py
amodbus/py.typed
amodbus/server/__init__.py
amodbus/server/base.py
amodbus/server/requesthandler.py
amodbus/server/server.py
amodbus/server/simulator/README.rst
amodbus/server/simulator/TODO.rst
amodbus/server/simulator/__init__.py
amodbus/server/simulator/custom_actions.py
amodbus/server/simulator/http_server.py
amodbus/server/simulator/main.py
amodbus/server/simulator/setup.json
amodbus/server/simulator/web/apple120.png
amodbus/server/simulator/web/apple152.png
amodbus/server/simulator/web/apple60.png
amodbus/server/simulator/web/apple76.png
amodbus/server/simulator/web/favicon.ico
amodbus/server/simulator/web/generator/calls
amodbus/server/simulator/web/generator/log
amodbus/server/simulator/web/generator/pymodbus_icon_original.png
amodbus/server/simulator/web/generator/registers
amodbus/server/simulator/web/generator/server
amodbus/server/simulator/web/index.html
amodbus/server/simulator/web/pymodbus.css
amodbus/server/simulator/web/welcome.html
amodbus/server/startstop.py
amodbus/simulator/__init__.py
amodbus/simulator/simcore.py
amodbus/simulator/simdata.py
amodbus/transaction/__init__.py
amodbus/transaction/transaction.py
amodbus-0.1.0.dist-info/AUTHORS.rst
amodbus-0.1.0.dist-info/LICENSE
amodbus-0.1.0.dist-info/METADATA
amodbus-0.1.0.dist-info/WHEEL
amodbus-0.1.0.dist-info/entry_points.txt
amodbus-0.1.0.dist-info/RECORD
