Metadata-Version: 2.3
Name: amodbus
Version: 0.1.0
Summary:  A properly async fork of pymodbus 
License: BSD-3-Clause
Keywords: modbus,asyncio,scada,client,server,simulator
Author: Upstream Data
Maintainer: UpstreamData
Requires-Python: >=3.10.0
Classifier: Development Status :: 4 - Beta
Classifier: Environment :: Console
Classifier: Framework :: AsyncIO
Classifier: Intended Audience :: Developers
Classifier: License :: OSI Approved :: BSD License
Classifier: Operating System :: POSIX :: Linux
Classifier: Operating System :: Unix
Classifier: Operating System :: MacOS :: MacOS X
Classifier: Operating System :: OS Independent
Classifier: Operating System :: Microsoft
Classifier: Programming Language :: Python :: 3.9
Classifier: Programming Language :: Python :: 3.10
Classifier: Programming Language :: Python :: 3.11
Classifier: Programming Language :: Python :: 3.12
Classifier: Programming Language :: Python :: 3.13
Classifier: Topic :: System :: Networking
Classifier: Topic :: Utilities
Requires-Dist: pyserial (>=3.5)
Project-URL: Bug Reports, https://github.com/UpstreamDataInc/amodbus/issues
Project-URL: Homepage, https://github.com/UpstreamDataInc/amodbus/
Project-URL: Source Code, https://github.com/UpstreamDataInc/amodbus
